vespricetracker/__init__.py
vespricetracker/__main__.py
vespricetracker/config/log_config.yaml
vespricetracker/core/__init__.py
vespricetracker/core/ad_fetch.py
vespricetracker/core/ad_filter.py
vespricetracker/core/ad_serializer.py
vespricetracker/core/bcv_fetch.py
vespricetracker/dto/__init__.py
vespricetracker/dto/ad_dto.py
vespricetracker/dto/ad_request_dto.py
vespricetracker/dto/bootstrap_paths_dto.py
vespricetracker/enums/__init__.py
vespricetracker/enums/payment_method.py
vespricetracker/exception/__init__.py
vespricetracker/exception/bootstrap_error.py
vespricetracker/model/__init__.py
vespricetracker/model/ves_usd_entity.py
vespricetracker/service/__init__.py
vespricetracker/service/ves_usd_service.py
vespricetracker/util/__init__.py
vespricetracker/util/file_importer.py
vespricetracker/util/static.py
vespricetracker/util/vespricetracker_logger.py
vespricetracker-1.1.8.dist-info/licenses/LICENSE
vespricetracker-1.1.8.dist-info/METADATA
vespricetracker-1.1.8.dist-info/WHEEL
vespricetracker-1.1.8.dist-info/entry_points.txt
vespricetracker-1.1.8.dist-info/top_level.txt
vespricetracker-1.1.8.dist-info/RECORD
