Metadata-Version: 2.4
Name: vespricetracker
Version: 1.1.8
Author-email: Carlos Florez <carlos@florez.co.uk>
Maintainer-email: Carlos Florez <carlos@florez.co.uk>
License: MIT License
Project-URL: Repository, https://github.com/florez-carlos/vespricetracker
Classifier: Development Status :: 5 - Production/Stable
Classifier: Programming Language :: Python :: 3.11
Requires-Python: >=3.11.6
License-File: LICENSE
Requires-Dist: colorlog==6.4.0
Requires-Dist: requests==2.32.3
Requires-Dist: selenium==4.29.0
Requires-Dist: pyyaml==6.0.1
Requires-Dist: toml==0.10.2
Requires-Dist: pywin32==306; sys_platform == "win32"
Requires-Dist: simplejson==3.20.1
Requires-Dist: boto3==1.37.22
Dynamic: license-file
